Pokesi/_init_.py
Pokesi/pokemon.csv
Pokesi/random_pokemon.py
Pokesi-1.0.3.dist-info/METADATA
Pokesi-1.0.3.dist-info/WHEEL
Pokesi-1.0.3.dist-info/top_level.txt
Pokesi-1.0.3.dist-info/RECORD
