Metadata-Version: 2.1
Name: Pokesi
Version: 1.0.3
Summary: Libreria que permite generar un Pokemon aleatorio
Author: Bryan Salazar
Author-email: bryan.nayrb.1071@gmail.com
Requires-Dist: pandas
